mkdocs_nbsync/__init__.py
mkdocs_nbsync/plugin.py
mkdocs_nbsync/py.typed
mkdocs_nbsync-0.1.5.dist-info/WHEEL
mkdocs_nbsync-0.1.5.dist-info/entry_points.txt
mkdocs_nbsync-0.1.5.dist-info/METADATA
mkdocs_nbsync-0.1.5.dist-info/RECORD
