Metadata-Version: 2.3
Name: mkdocs-nbsync
Version: 0.1.5
Summary: MkDocs plugin treating Jupyter notebooks, Python scripts and Markdown files as first-class citizens for documentation with dynamic execution and real-time synchronization
Keywords: jupyter,notebook,mkdocs,documentation,markdown,python,visualization,dynamic-execution,real-time-sync
Author: daizutabi
Author-email: daizutabi <daizutabi@gmail.com>
License: MIT License
Classifier: Development Status :: 4 - Beta
Classifier: Programming Language :: Python
Classifier: Programming Language :: Python :: 3.10
Classifier: Programming Language :: Python :: 3.11
Classifier: Programming Language :: Python :: 3.12
Classifier: Programming Language :: Python :: 3.13
Classifier: Programming Language :: Python :: 3.14
Classifier: Topic :: Documentation
Classifier: Topic :: Software Development :: Documentation
Classifier: Topic :: Text Processing :: Markup :: Markdown
Requires-Dist: mkdocs>=1.6
Requires-Dist: nbsync>=0.3.6
Requires-Python: >=3.10
Project-URL: Documentation, https://daizutabi.github.io/mkdocs-nbsync/
Project-URL: Issues, https://github.com/daizutabi/mkdocs-nbsync/issues
Project-URL: Source, https://github.com/daizutabi/mkdocs-nbsync
